drf_tus-2.0.3.dist-info/licenses/AUTHORS.rst
drf_tus-2.0.3.dist-info/licenses/LICENSE
rest_framework_tus/__init__.py
rest_framework_tus/apps.py
rest_framework_tus/compat.py
rest_framework_tus/constants.py
rest_framework_tus/exceptions.py
rest_framework_tus/middleware.py
rest_framework_tus/models.py
rest_framework_tus/parsers.py
rest_framework_tus/receivers.py
rest_framework_tus/routers.py
rest_framework_tus/serializers.py
rest_framework_tus/settings.py
rest_framework_tus/signals.py
rest_framework_tus/states.py
rest_framework_tus/storage.py
rest_framework_tus/urls.py
rest_framework_tus/utils.py
rest_framework_tus/views.py
rest_framework_tus/migrations/0001_initial.py
rest_framework_tus/migrations/0002_auto_20170406_0620.py
rest_framework_tus/migrations/0003_auto_20170619_0358.py
rest_framework_tus/migrations/0004_alter_upload_id_alter_upload_upload_metadata.py
rest_framework_tus/migrations/0005_alter_upload_uploaded_file.py
rest_framework_tus/migrations/__init__.py
drf_tus-2.0.3.dist-info/METADATA
drf_tus-2.0.3.dist-info/WHEEL
drf_tus-2.0.3.dist-info/top_level.txt
drf_tus-2.0.3.dist-info/RECORD
