Metadata-Version: 2.4
Name: drf-tus
Version: 2.0.3
Summary: A Tus (tus.io) library for Django Rest Framework
Author-email: Dirk Moors <dirkmoors@gmail.com>
License: MIT
Project-URL: homepage, https://github.com/dirkmoors/drf-tus
Project-URL: changelog, https://github.com/dirkmoors/drf-tus/blob/master/HISTORY.rst
Keywords: drf-tus,tus,django,rest,framework,django-rest-framework
Classifier: Development Status :: 5 - Production/Stable
Classifier: Framework :: Django
Classifier: Framework :: Django :: 3.2
Classifier: Framework :: Django :: 4.0
Classifier: Framework :: Django :: 4.1
Classifier: Framework :: Django :: 4.2
Classifier: Framework :: Django :: 5.0
Classifier: Framework :: Django :: 5.1
Classifier: Framework :: Django :: 6.0
Classifier: Intended Audience :: Developers
Classifier: License :: OSI Approved :: MIT License
Classifier: Natural Language :: English
Classifier: Programming Language :: Python :: 3.8
Classifier: Programming Language :: Python :: 3.9
Classifier: Programming Language :: Python :: 3.10
Classifier: Programming Language :: Python :: 3.11
Classifier: Programming Language :: Python :: 3.12
Classifier: Programming Language :: Python :: 3.13
Classifier: Programming Language :: Python :: 3.14
Classifier: Topic :: Software Development :: Libraries :: Python Modules
License-File: LICENSE
License-File: AUTHORS.rst
Requires-Dist: python-dateutil>=2.8.2
Requires-Dist: Django<7.0,>=3.2
Requires-Dist: djangorestframework>=3.14.0
Requires-Dist: jsonfield>=2.0.0
Requires-Dist: django-fsm==2.8.1
Requires-Dist: six>=1.11.0
Dynamic: license-file
